agecal/__init__.py
agecal/__main__.py
agecal/compareage.py
agecal/greeting.py
agecal_mick-3.0.2.dist-info/METADATA
agecal_mick-3.0.2.dist-info/WHEEL
agecal_mick-3.0.2.dist-info/entry_points.txt
agecal_mick-3.0.2.dist-info/top_level.txt
agecal_mick-3.0.2.dist-info/RECORD
