Metadata-Version: 2.1
Name: agecal-mick
Version: 3.0.2
Summary: Compare age with mickzaa return older or younger
Home-page: UNKNOWN
Author: Mickzaa
License: MIT
Platform: UNKNOWN
Classifier: License :: OSI Approved :: MIT License
Classifier: Programming Language :: Python
Classifier: Programming Language :: Python :: 2
Classifier: Programming Language :: Python :: 3
